Winglets/__init__.py
Winglets/server.py
Winglets/handler/__init__.py
Winglets/handler/buttonhandler.py
Winglets/handler/drawhandler.py
Winglets/handler/geoOperation.py
Winglets/handler/handler_all.py
Winglets/handler/kdehandler.py
Winglets/handler/mongohandler.py
Winglets/handler/wingletstephandler.py
wingletsPyFolder/__init__.py
wingletsPyFolder/server.py
Winglets-0.1.0.dist-info/LICENSE
Winglets-0.1.0.dist-info/METADATA
Winglets-0.1.0.dist-info/WHEEL
Winglets-0.1.0.dist-info/top_level.txt
Winglets-0.1.0.dist-info/RECORD
