Metadata-Version: 2.1
Name: Winglets
Version: 0.1.0
Summary: Winglets by Python
Home-page: https://github.com/DarkDisasters/Winglets
Author: Shuaiqi Wang
Author-email: shuaiqiwang666@gmail.com
License: MIT
Platform: UNKNOWN
Classifier: License :: OSI Approved :: MIT License
Classifier: Programming Language :: Python
Classifier: Programming Language :: Python :: 3
Classifier: Programming Language :: Python :: 3.6
Classifier: Programming Language :: Python :: Implementation :: CPython
Classifier: Programming Language :: Python :: Implementation :: PyPy
Requires-Python: >=3.6.0
